FastCG/__init__.py
FastCG/generators/GeneratorBase.py
FastCG/generators/ProbKnnGenerator.py
FastCG/generators/__init__.py
FastCG/utils/SmartCondition.py
FastCG/utils/__init__.py
FastCG/utils/logger.py
FastCG/utils/util_functions.py
FastCG-0.0.3.dist-info/METADATA
FastCG-0.0.3.dist-info/WHEEL
FastCG-0.0.3.dist-info/top_level.txt
FastCG-0.0.3.dist-info/RECORD
